[
  {
    "vehicle_id": "V001",
    "timestamp": 1744687469699,
    "data_type": "telemetry",
    "mode": "idle",
    "battery": {
      "soc": 92.5,
      "temperature": 24.3,
      "cycle_count": 80,
      "voltage": 384.5,
      "current": 0.6
    },
    "motor": {
      "temperature": 25.4,
      "efficiency": 92.0,
      "load": 0.0,
      "rpm": 0,
      "torque": 0.0
    },
    "sensors": {
      "acceleration": {
        "x": 0.05,
        "y": 0.0,
        "z": 9.81
      },
      "gps": {
        "latitude": 39.840625025129654,
        "longitude": 116.38472680867767,
        "altitude": 52.6131222245789,
        "speed": 0.0,
        "heading": 5.4
      },
      "gyroscope": {
        "x": 0.0,
        "y": -0.03,
        "z": -0.03
      }
    }
  },
  {
    "vehicle_id": "V002",
    "timestamp": 1744687469699,
    "data_type": "telemetry",
    "mode": "idle",
    "battery": {
      "soc": 89.1,
      "temperature": 21.1,
      "cycle_count": 115,
      "voltage": 383.8,
      "current": -0.7
    },
    "motor": {
      "temperature": 27.1,
      "efficiency": 91.8,
      "load": 0.0,
      "rpm": 0,
      "torque": 0.0
    },
    "sensors": {
      "acceleration": {
        "x": 0.09,
        "y": 0.04,
        "z": 9.76
      },
      "gps": {
        "latitude": 39.81405393613799,
        "longitude": 116.39057746005953,
        "altitude": 45.265332160505146,
        "speed": 0.0,
        "heading": 126.7
      },
      "gyroscope": {
        "x": 0.04,
        "y": -0.03,
        "z": -0.02
      }
    }
  },
  {
    "vehicle_id": "V003",
    "timestamp": 1744687469699,
    "data_type": "telemetry",
    "mode": "idle",
    "battery": {
      "soc": 77.3,
      "temperature": 24.7,
      "cycle_count": 108,
      "voltage": 381.5,
      "current": -0.4
    },
    "motor": {
      "temperature": 26.8,
      "efficiency": 91.8,
      "load": 0.0,
      "rpm": 0,
      "torque": 0.0
    },
    "sensors": {
      "acceleration": {
        "x": -0.01,
        "y": 0.09,
        "z": 9.72
      },
      "gps": {
        "latitude": 39.9454458000118,
        "longitude": 116.39159511231416,
        "altitude": 54.70854184015606,
        "speed": 0.0,
        "heading": 90.7
      },
      "gyroscope": {
        "x": -0.01,
        "y": -0.04,
        "z": -0.02
      }
    }
  },
  {
    "vehicle_id": "V004",
    "timestamp": 1744687469699,
    "data_type": "telemetry",
    "mode": "idle",
    "battery": {
      "soc": 93.0,
      "temperature": 23.4,
      "cycle_count": 189,
      "voltage": 384.6,
      "current": 0.2
    },
    "motor": {
      "temperature": 24.8,
      "efficiency": 92.0,
      "load": 0.0,
      "rpm": 0,
      "torque": 0.0
    },
    "sensors": {
      "acceleration": {
        "x": -0.07,
        "y": -0.07,
        "z": 9.86
      },
      "gps": {
        "latitude": 39.97585849823584,
        "longitude": 116.4472840581235,
        "altitude": 46.1714359744961,
        "speed": 0.0,
        "heading": 244.4
      },
      "gyroscope": {
        "x": 0.03,
        "y": -0.04,
        "z": 0.04
      }
    }
  },
  {
    "vehicle_id": "V005",
    "timestamp": 1744687469699,
    "data_type": "telemetry",
    "mode": "idle",
    "battery": {
      "soc": 90.4,
      "temperature": 21.1,
      "cycle_count": 118,
      "voltage": 384.1,
      "current": -0.5
    },
    "motor": {
      "temperature": 27.2,
      "efficiency": 91.8,
      "load": 0.0,
      "rpm": 0,
      "torque": 0.0
    },
    "sensors": {
      "acceleration": {
        "x": 0.09,
        "y": 0.05,
        "z": 9.76
      },
      "gps": {
        "latitude": 39.888938567132826,
        "longitude": 116.47411681408268,
        "altitude": 52.695750042102176,
        "speed": 0.0,
        "heading": 31.8
      },
      "gyroscope": {
        "x": 0.04,
        "y": 0.05,
        "z": -0.03
      }
    }
  }
]